pdf_file_renamer/__init__.py
pdf_file_renamer/main.py
pdf_file_renamer/application/__init__.py
pdf_file_renamer/application/filename_service.py
pdf_file_renamer/application/pdf_rename_workflow.py
pdf_file_renamer/application/rename_service.py
pdf_file_renamer/domain/__init__.py
pdf_file_renamer/domain/models.py
pdf_file_renamer/domain/ports.py
pdf_file_renamer/infrastructure/__init__.py
pdf_file_renamer/infrastructure/config.py
pdf_file_renamer/infrastructure/doi/__init__.py
pdf_file_renamer/infrastructure/doi/pdf2doi_extractor.py
pdf_file_renamer/infrastructure/llm/__init__.py
pdf_file_renamer/infrastructure/llm/pydantic_ai_provider.py
pdf_file_renamer/infrastructure/pdf/__init__.py
pdf_file_renamer/infrastructure/pdf/composite.py
pdf_file_renamer/infrastructure/pdf/docling_extractor.py
pdf_file_renamer/infrastructure/pdf/pymupdf_extractor.py
pdf_file_renamer/presentation/__init__.py
pdf_file_renamer/presentation/cli.py
pdf_file_renamer/presentation/formatters.py
pdf_file_renamer-0.6.3.dist-info/METADATA
pdf_file_renamer-0.6.3.dist-info/WHEEL
pdf_file_renamer-0.6.3.dist-info/entry_points.txt
pdf_file_renamer-0.6.3.dist-info/licenses/LICENSE
pdf_file_renamer-0.6.3.dist-info/RECORD
