Metadata-Version: 2.4
Name: pdf-file-renamer
Version: 0.6.3
Summary: Intelligent PDF renaming using LLMs with DOI-based naming and interactive workflow
Project-URL: Homepage, https://github.com/nostoslabs/pdf-renamer
Project-URL: Repository, https://github.com/nostoslabs/pdf-renamer
Project-URL: Issues, https://github.com/nostoslabs/pdf-renamer/issues
Project-URL: Changelog, https://github.com/nostoslabs/pdf-renamer/blob/main/CHANGELOG.md
Author-email: Nostos Labs <info@nostoslabs.com>
License: MIT
License-File: LICENSE
Keywords: academic-papers,ai,automation,document-management,doi,file-organization,llm,pdf,rename
Classifier: Development Status :: 4 - Beta
Classifier: Environment :: Console
Classifier: Intended Audience :: Education
Classifier: Intended Audience :: End Users/Desktop
Classifier: Intended Audience :: Science/Research
Classifier: License :: OSI Approved :: MIT License
Classifier: Operating System :: OS Independent
Classifier: Programming Language :: Python :: 3
Classifier: Programming Language :: Python :: 3.11
Classifier: Programming Language :: Python :: 3.12
Classifier: Topic :: Office/Business :: Office Suites
Classifier: Topic :: Scientific/Engineering
Classifier: Topic :: Text Processing :: General
Classifier: Topic :: Utilities
Classifier: Typing :: Typed
Requires-Python: >=3.11
Requires-Dist: docling-core>=2.0.0
Requires-Dist: docling-parse>=2.0.0
Requires-Dist: pdf2doi>=1.7
Requires-Dist: pydantic-ai>=1.0.17
Requires-Dist: pydantic-settings>=2.7.1
Requires-Dist: pydantic>=2.10.6
Requires-Dist: pymupdf>=1.26.5
Requires-Dist: python-dotenv>=1.1.1
Requires-Dist: rich>=14.2.0
Requires-Dist: tenacity>=9.0.0
Requires-Dist: typer>=0.19.2
Provides-Extra: dev
Requires-Dist: mypy>=1.14.1; extra == 'dev'
Requires-Dist: pytest-asyncio>=0.25.2; extra == 'dev'
Requires-Dist: pytest-cov>=6.0.0; extra == 'dev'
Requires-Dist: pytest-mock>=3.14.0; extra == 'dev'
Requires-Dist: pytest>=8.3.4; extra == 'dev'
Requires-Dist: ruff>=0.9.1; extra == 'dev'
